Metadata-Version: 2.1
Name: tycho-1
Version: 1.0.0
Summary: Tycho is an API, compiler, and executor for cloud native distributed systems.
Home-page: https://github.com/helxplatform/tycho.git
Maintainer: Renci
Maintainer-email: muralikarthik.k@renci.org
License: UNKNOWN
Platform: UNKNOWN
Classifier: Programming Language :: Python :: 3
Classifier: License :: OSI Approved :: MIT License
Classifier: Operating System :: OS Independent
Requires-Python: >=3.7
Requires-Dist: Flask (==1.0.2)
Requires-Dist: Flask-Cors (==3.0.7)
Requires-Dist: Flask-RESTful (==0.3.7)
Requires-Dist: Jinja2 (==2.10)
Requires-Dist: MarkupSafe (==1.1.1)
Requires-Dist: PyJWT (==1.7.1)
Requires-Dist: PyYAML (==3.13)
Requires-Dist: Werkzeug (==0.14.1)
Requires-Dist: adal (==1.2.1)
Requires-Dist: aniso8601 (==4.1.0)
Requires-Dist: asn1crypto (==0.24.0)
Requires-Dist: atomicwrites (==1.3.0)
Requires-Dist: attrs (==18.2.0)
Requires-Dist: bcrypt (==3.2.0)
Requires-Dist: cached-property (==1.5.2)
Requires-Dist: cachetools (==3.1.0)
Requires-Dist: certifi (==2018.11.29)
Requires-Dist: cffi (==1.14.3)
Requires-Dist: chardet (==3.0.4)
Requires-Dist: coverage (==5.3)
Requires-Dist: cryptography (==2.5)
Requires-Dist: docker (==3.7.3)
Requires-Dist: docker-compose (==1.24.1)
Requires-Dist: docker-pycreds (==0.4.0)
Requires-Dist: dockerpty (==0.4.1)
Requires-Dist: docopt (==0.6.2)
Requires-Dist: flasgger (==0.9.2)
Requires-Dist: gitdb (==4.0.5)
Requires-Dist: gitpython (==3.1.11)
Requires-Dist: google-auth (==1.6.3)
Requires-Dist: gunicorn (==19.9.0)
Requires-Dist: idna (==2.7)
Requires-Dist: itsdangerous (==1.1.0)
Requires-Dist: jsonschema (==2.6.0)
Requires-Dist: kubernetes (==8.0.1)
Requires-Dist: mistune (==0.8.4)
Requires-Dist: more-itertools (==6.0.0)
Requires-Dist: netifaces
Requires-Dist: oauthlib (==3.0.1)
Requires-Dist: paramiko (==2.7.2)
Requires-Dist: pluggy (==0.9.0)
Requires-Dist: py (==1.8.0)
Requires-Dist: pyasn1 (==0.4.5)
Requires-Dist: pyasn1-modules (==0.2.4)
Requires-Dist: pycparser (==2.19)
Requires-Dist: pynacl (==1.4.0)
Requires-Dist: pyrsistent (==0.14.11)
Requires-Dist: pytest (==4.3.0)
Requires-Dist: pytest-cov (==2.7.1)
Requires-Dist: pytest-mock (==1.10.4)
Requires-Dist: python-dateutil (==2.8.0)
Requires-Dist: pytz (==2018.9)
Requires-Dist: requests (==2.20.1)
Requires-Dist: requests-cache (==0.5.2)
Requires-Dist: requests-oauthlib (==1.2.0)
Requires-Dist: rsa (==4.0)
Requires-Dist: six (==1.12.0)
Requires-Dist: smmap (==3.0.4)
Requires-Dist: texttable (==0.9.1)
Requires-Dist: urllib3 (==1.24.1)
Requires-Dist: websocket-client (==0.55.0)
Requires-Dist: Click (==7.0)
